{
  "branch": "minecolonies:civilian",
  "effects": [
    {
      "minecolonies:effects/undertakerrun": 1
    }
  ],
  "icon": "minecolonies:blockhutgraveyard",
  "parentResearch": "minecolonies:civilian/remembrance",
  "requirements": [
    {
      "building": "graveyard",
      "level": 2
    },
    {
      "type": "minecolonies:item_list",
      "item": {
        "items": [
          "minecraft:iron_boots"
        ]
      },
      "quantity": 1
    }
  ],
  "researchLevel": 2,
  "sortOrder": 3
}