{
  "parent": "minecolonies:block/blockhutmechanic",
  "display": {
    "thirdperson_righthand": {
      "rotation": [45, 45, 0],
      "translation": [0, 2.5, 0],
      "scale": [0.375, 0.375, 0.375]
    },
    "thirdperson_lefthand": {
      "rotation": [45, 45, 0],
      "translation": [0, 2.5, 0],
      "scale": [0.375, 0.375, 0.375]
    },
    "firstperson_righthand": {
      "rotation": [0, 110, 0],
      "translation": [0, 1.25, 0],
      "scale": [0.4, 0.4, 0.4]
    },
    "firstperson_lefthand": {
      "rotation": [0, 110, 0],
      "translation": [0, 1.25, 0],
      "scale": [0.4, 0.4, 0.4]
    },
    "ground": {
      "translation": [0, 3, 0],
      "scale": [0.25, 0.25, 0.25]
    },
    "gui": {
      "rotation": [30, 225, 0],
      "translation": [1.5, 0, 0],
      "scale": [0.7, 0.7, 0.7]
    },
    "head": {
      "translation": [0, 1.75, -1.75]
    },
    "fixed": {
      "translation": [0, 0, -0.75],
      "scale": [0.55, 0.55, 0.55]
    }
  }
}
