{
  "parent": "minecolonies:minecolonies/build_wonder",
  "display": {
    "icon": {
      "item": "minecolonies:blockhutwonder"
    },
    "title": {
      "translate": "advancements.minecolonies.build.wonder_5.title"
    },
    "description": {
      "translate": "advancements.minecolonies.build.wonder_5.description"
    },
    "show_toast": true,
    "announce_to_chat": true
  },
  "criteria": {
    "warehouse": {
      "trigger": "minecolonies:complete_build_request",
      "conditions": {
        "hut_name": "wonder",
        "level": 5
      }
    }
  }
}