{
  "parent": "minecolonies:minecolonies/colony_population_25",
  "display": {
    "icon": {
      "item": "minecraft:diamond"
    },
    "title": {
      "translate": "advancements.minecolonies.colony_population_50.title"
    },
    "description": {
      "translate": "advancements.minecolonies.colony_population_50.description"
    },
    "show_toast": true,
    "announce_to_chat": true,
    "frame": "challenge"
  },
  "criteria": {
    "population_5": {
      "trigger": "minecolonies:colony_population",
      "conditions": {
        "population_count": 50
      }
    }
  }
}