{
  "parent": "minecolonies:minecolonies/start_builder",
  "criteria": {
    "add_recipe_torch": {
      "conditions": {
        "crafting_size": 2,
        "items": [
          {
            "items": "minecraft:torch"
          }
        ]
      },
      "trigger": "minecolonies:building_add_recipe"
    }
  },
  "display": {
    "description": {
      "translate": "advancements.minecolonies.building_add_recipe_torch.description"
    },
    "icon": {
      "count": 1,
      "id": "minecraft:torch"
    },
    "title": {
      "translate": "advancements.minecolonies.building_add_recipe_torch.title"
    }
  },
  "requirements": [
    [
      "add_recipe_torch"
    ]
  ],
  "sends_telemetry_event": true
}